{
  "start_date": "2026-06-13",
  "end_date": "2026-07-31",
  "bet_per_note": 2,
  "prize_per_hit": 160,
  "max_notes_per_day": 10,
  "records": [
    {
      "date": "2026-06-12",
      "draw": "2026153",
      "draw_nums": [
        8,
        8,
        7
      ],
      "draw_type": "组三",
      "recommendations": [],
      "notes": 0,
      "cost": 0,
      "hits": 0,
      "prize": 0,
      "daily_pnl": 0,
      "reason": "熔断未推"
    },
    {
      "date": "2026-06-13",
      "draw": "2026154",
      "draw_nums": [
        3,
        7,
        7
      ],
      "draw_type": "组三",
      "recommendations": [
        [
          4,
          5,
          9
        ],
        [
          0,
          3,
          6
        ],
        [
          1,
          4,
          7
        ],
        [
          2,
          5,
          9
        ],
        [
          0,
          5,
          6
        ],
        [
          1,
          3,
          9
        ],
        [
          2,
          3,
          5
        ]
      ],
      "notes": 7,
      "cost": 14,
      "hits": 0,
      "prize": 0,
      "daily_pnl": -14,
      "reason": "组六7注全未命中组三开奖"
    },
    {
      "date": "2026-06-14",
      "draw": "2026155",
      "draw_nums": [
        4,
        0,
        9
      ],
      "draw_type": "组六",
      "recommendations": [
        [
          0,
          4,
          5
        ],
        [
          1,
          5,
          9
        ],
        [
          0,
          1,
          4
        ],
        [
          2,
          5,
          8
        ],
        [
          3,
          6,
          9
        ],
        [
          0,
          5,
          9
        ],
        [
          1,
          4,
          7
        ],
        [
          2,
          4,
          6
        ],
        [
          3,
          4,
          8
        ],
        [
          0,
          2,
          5
        ]
      ],
      "notes": 10,
      "cost": 20,
      "hits": 0,
      "prize": 0,
      "daily_pnl": -20,
      "reason": "用户手动关闭熔断, 组六10注未命中开奖409"
    },
    {
      "date": "2026-06-15",
      "draw": "2026156",
      "draw_nums": [
        1,
        6,
        2
      ],
      "draw_type": "组六",
      "recommendations": [
        [
          0,
          5,
          7
        ],
        [
          1,
          4,
          6
        ],
        [
          2,
          5,
          8
        ],
        [
          1,
          3,
          5
        ],
        [
          3,
          6,
          9
        ],
        [
          0,
          2,
          5
        ],
        [
          5,
          7,
          8
        ],
        [
          1,
          5,
          9
        ],
        [
          3,
          5,
          6
        ],
        [
          0,
          1,
          8
        ]
      ],
      "notes": 10,
      "cost": 20,
      "hits": 0,
      "prize": 0,
      "daily_pnl": -20,
      "reason": "组六10注未命中开奖162"
    },
    {
      "date": "2026-06-16",
      "draw": "2026157",
      "draw_nums": [
        3,
        2,
        7
      ],
      "draw_type": "组六",
      "recommendations": [
        [
          3,
          5,
          8
        ],
        [
          0,
          4,
          7
        ],
        [
          2,
          3,
          5
        ],
        [
          0,
          6,
          8
        ],
        [
          0,
          5,
          8
        ],
        [
          0,
          4,
          8
        ],
        [
          2,
          3,
          8
        ],
        [
          1,
          3,
          6
        ],
        [
          3,
          5,
          6
        ],
        [
          3,
          5,
          7
        ]
      ],
      "notes": 10,
      "cost": 20,
      "hits": 0,
      "prize": 0,
      "daily_pnl": -20,
      "reason": "组六10注未命中开奖327"
    },
    {
      "date": "2026-06-17",
      "draw": "2026158",
      "draw_nums": [
        1,
        7,
        8
      ],
      "draw_type": "组六",
      "recommendations": [
        [
          0,
          5,
          8
        ],
        [
          1,
          5,
          4
        ],
        [
          1,
          3,
          6
        ],
        [
          2,
          5,
          9
        ],
        [
          3,
          5,
          6
        ],
        [
          4,
          5,
          8
        ],
        [
          5,
          6,
          9
        ],
        [
          0,
          3,
          4
        ],
        [
          5,
          7,
          8
        ],
        [
          0,
          1,
          5
        ]
      ],
      "notes": 10,
      "cost": 20,
      "hits": 0,
      "prize": 0,
      "daily_pnl": -20,
      "reason": "组六10注→0命中开奖178组六"
    },
    {
      "date": "2026-06-18",
      "draw": "2026159",
      "draw_nums": [
        9,
        9,
        5
      ],
      "draw_type": "组三",
      "recommendations": [
        [
          0,
          5,
          6
        ],
        [
          2,
          5,
          7
        ],
        [
          3,
          5,
          8
        ],
        [
          0,
          2,
          5
        ],
        [
          1,
          4,
          5
        ],
        [
          3,
          4,
          7
        ],
        [
          0,
          1,
          9
        ],
        [
          2,
          3,
          6
        ],
        [
          4,
          6,
          9
        ],
        [
          0,
          5,
          9
        ]
      ],
      "notes": 10,
      "cost": 20,
      "hits": 0,
      "prize": 0,
      "daily_pnl": -20,
      "reason": "组六10注未命中开奖995组三"
    },
    {
      "date": "2026-06-19",
      "draw": "2026160",
      "draw_nums": [
        3,
        3,
        2
      ],
      "draw_type": "组三",
      "recommendations": [],
      "notes": 0,
      "cost": 0,
      "hits": 0,
      "prize": 0,
      "daily_pnl": 0,
      "reason": "自动化未运行，未推注"
    },
    {
      "date": "2026-06-20",
      "draw": "2026161",
      "draw_nums": [
        5,
        2,
        9
      ],
      "draw_type": "组六",
      "recommendations": [],
      "notes": 0,
      "cost": 0,
      "hits": 0,
      "prize": 0,
      "daily_pnl": 0,
      "reason": "自动化未运行，未推注"
    },
    {
      "date": "2026-06-21",
      "draw": "2026162",
      "draw_nums": [
        5,
        8,
        5
      ],
      "draw_type": "组三",
      "recommendations": [],
      "notes": 0,
      "cost": 0,
      "hits": 0,
      "prize": 0,
      "daily_pnl": 0,
      "reason": "自动化未运行，未推注"
    },
    {
      "date": "2026-06-22",
      "draw": "2026163",
      "draw_nums": [
        5,
        3,
        7
      ],
      "draw_type": "组六",
      "recommendations": [],
      "notes": 0,
      "cost": 0,
      "hits": 0,
      "prize": 0,
      "daily_pnl": 0,
      "reason": "自动化未运行，未推注"
    },
    {
      "date": "2026-06-23",
      "draw": "2026164",
      "draw_nums": [
        6,
        9,
        0
      ],
      "draw_type": "组六",
      "recommendations": [],
      "notes": 0,
      "cost": 0,
      "hits": 0,
      "prize": 0,
      "daily_pnl": 0,
      "reason": "自动化未运行，未推注"
    },
    {
      "date": "2026-06-24",
      "draw": "2026165",
      "draw_nums": [
        4,
        2,
        4
      ],
      "draw_type": "组三",
      "recommendations": [
        [
          1,
          2,
          4
        ],
        [
          3,
          7,
          8
        ],
        [
          3,
          4,
          7
        ],
        [
          0,
          1,
          2
        ],
        [
          0,
          4,
          9
        ],
        [
          1,
          2,
          9
        ],
        [
          3,
          4,
          8
        ],
        [
          2,
          5,
          8
        ],
        [
          3,
          4,
          6
        ],
        [
          3,
          4,
          9
        ]
      ],
      "notes": 10,
      "cost": 20,
      "hits": 0,
      "prize": 0,
      "daily_pnl": -20,
      "reason": "组六10注未命中开奖424组三"
    },
    {
      "date": "2026-06-25",
      "draw": "2026166",
      "draw_nums": [
        9,
        0,
        0
      ],
      "draw_type": "组三",
      "recommendations": [
        [
          1,
          3,
          8
        ],
        [
          0,
          5,
          7
        ],
        [
          1,
          2,
          3
        ],
        [
          0,
          7,
          8
        ],
        [
          1,
          3,
          9
        ],
        [
          0,
          4,
          8
        ],
        [
          2,
          3,
          8
        ],
        [
          2,
          3,
          9
        ],
        [
          3,
          4,
          8
        ],
        [
          1,
          3,
          6
        ]
      ],
      "notes": 10,
      "cost": 20,
      "hits": 0,
      "prize": 0,
      "daily_pnl": -20,
      "reason": "熔断未触发(组三1连)，正常推10注组六。核心锚点: 1(缺7期)+8(缺3期) | 结算: 组六10注0命中开奖900组三"
    },
    {
      "date": "2026-06-26",
      "draw": "2026167",
      "draw_nums": [
        6,
        3,
        1
      ],
      "draw_type": "组六",
      "recommendations": [
        [
          1,
          3,
          8
        ],
        [
          5,
          6,
          7
        ],
        [
          1,
          2,
          3
        ],
        [
          0,
          7,
          8
        ],
        [
          1,
          3,
          9
        ],
        [
          0,
          4,
          8
        ],
        [
          1,
          3,
          6
        ],
        [
          0,
          2,
          3
        ],
        [
          0,
          4,
          9
        ],
        [
          1,
          3,
          7
        ]
      ],
      "notes": 10,
      "cost": 20,
      "hits": 1,
      "prize": 160,
      "daily_pnl": 140,
      "reason": "组六10注→1命中1 3 6开奖631组六"
    },
    {
      "date": "2026-06-27",
      "draw": "2026168",
      "draw_nums": [
        1,
        3,
        0
      ],
      "draw_type": "组六",
      "recommendations": [
        [
          5,
          7,
          8
        ],
        [
          0,
          2,
          4
        ],
        [
          2,
          3,
          8
        ],
        [
          0,
          5,
          8
        ],
        [
          0,
          5,
          7
        ],
        [
          0,
          3,
          8
        ],
        [
          0,
          2,
          7
        ],
        [
          0,
          2,
          6
        ],
        [
          1,
          3,
          8
        ],
        [
          3,
          4,
          8
        ]
      ],
      "notes": 10,
      "cost": 20,
      "hits": 0,
      "prize": 0,
      "daily_pnl": -20,
      "reason": "组六10注→0命中开奖130组六"
    },
    {
      "date": "2026-06-28",
      "draw": "2026169",
      "draw_nums": [
        8,
        3,
        2
      ],
      "draw_type": "组六",
      "recommendations": [],
      "notes": 0,
      "cost": 0,
      "hits": 0,
      "prize": 0,
      "daily_pnl": 0,
      "reason": "熔断未推(组三过热+组六2连观望)，开奖832组六"
    },
    {
      "date": "2026-06-29",
      "draw": "2026170",
      "draw_nums": [
        8,
        0,
        5
      ],
      "draw_type": "组六",
      "recommendations": [
        [
          4,
          5,
          7
        ],
        [
          2,
          5,
          7
        ],
        [
          0,
          5,
          8
        ],
        [
          3,
          4,
          5
        ],
        [
          2,
          5,
          6
        ],
        [
          0,
          4,
          7
        ],
        [
          0,
          5,
          9
        ],
        [
          3,
          4,
          7
        ],
        [
          4,
          6,
          9
        ],
        [
          1,
          3,
          7
        ]
      ],
      "notes": 10,
      "cost": 20,
      "hits": 1,
      "prize": 160,
      "daily_pnl": 140,
      "reason": "组六10注->1命中[[0, 5, 8]] 开奖805组六, 日盈亏140元"
    },
    {
      "date": "2026-06-30",
      "draw": "2026171",
      "draw_nums": [
        1,
        3,
        4
      ],
      "draw_type": "组六",
      "recommendations": [
        [
          4,
          7,
          9
        ],
        [
          1,
          2,
          6
        ],
        [
          2,
          7,
          8
        ],
        [
          0,
          4,
          7
        ],
        [
          0,
          6,
          7
        ],
        [
          0,
          4,
          8
        ],
        [
          3,
          7,
          8
        ],
        [
          0,
          2,
          4
        ],
        [
          2,
          3,
          6
        ],
        [
          1,
          7,
          8
        ]
      ],
      "notes": 10,
      "cost": 20,
      "hits": 0,
      "prize": 0,
      "daily_pnl": -20,
      "reason": "组六10注->0命中 开奖134组六"
    },
    {
      "date": "2026-07-01",
      "draw": "2026172",
      "draw_nums": [
        4,
        4,
        5
      ],
      "draw_type": "组三",
      "recommendations": [
        [
          6,
          7,
          9
        ],
        [
          0,
          2,
          8
        ],
        [
          2,
          7,
          8
        ],
        [
          3,
          7,
          9
        ],
        [
          0,
          6,
          7
        ],
        [
          0,
          3,
          9
        ],
        [
          0,
          7,
          8
        ],
        [
          2,
          3,
          9
        ],
        [
          1,
          3,
          4
        ],
        [
          1,
          7,
          8
        ]
      ],
      "notes": 10,
      "cost": 20,
      "hits": 0,
      "prize": 0,
      "daily_pnl": -20,
      "reason": "组六10注->0命中 开奖445组三"
    },
    {
      "date": "2026-07-02",
      "draw": "2026173",
      "draw_nums": [
        6,
        7,
        7
      ],
      "draw_type": "组三",
      "recommendations": [],
      "notes": 0,
      "cost": 0,
      "hits": 0,
      "prize": 0,
      "daily_pnl": 0,
      "reason": "组六0注->0命中 开奖677组三"
    },
    {
      "date": "2026-07-03",
      "draw": "2026174",
      "draw_nums": [
        6,
        1,
        8
      ],
      "draw_type": "组六",
      "recommendations": [
        [
          2,
          8,
          9
        ],
        [
          0,
          1,
          3
        ],
        [
          7,
          8,
          9
        ],
        [
          0,
          4,
          9
        ],
        [
          1,
          2,
          9
        ],
        [
          2,
          7,
          9
        ],
        [
          2,
          3,
          8
        ],
        [
          3,
          5,
          6
        ],
        [
          2,
          3,
          9
        ],
        [
          2,
          4,
          9
        ]
      ],
      "notes": 10,
      "cost": 20,
      "hits": 0,
      "prize": 0,
      "daily_pnl": -20,
      "reason": "组六10注->0命中 开奖618组六"
    },
    {
      "date": "2026-07-04",
      "draw": "2026175",
      "draw_nums": [
        4,
        2,
        1
      ],
      "draw_type": "组六",
      "recommendations": [],
      "notes": 0,
      "cost": 0,
      "hits": 0,
      "prize": 0,
      "daily_pnl": 0,
      "reason": "组六0注->0命中 开奖421组六"
    },
    {
      "date": "2026-07-05",
      "draw": "2026176",
      "draw_nums": [
        2,
        6,
        9
      ],
      "draw_type": "组六",
      "recommendations": [],
      "notes": 0,
      "cost": 0,
      "hits": 0,
      "prize": 0,
      "daily_pnl": 0,
      "reason": "组六0注->0命中 开奖269组六"
    },
    {
      "date": "2026-07-06",
      "draw": "2026177",
      "draw_nums": [
        8,
        0,
        8
      ],
      "draw_type": "组三",
      "recommendations": [
        [
          0,
          3,
          5
        ],
        [
          4,
          7,
          8
        ],
        [
          0,
          2,
          7
        ],
        [
          3,
          6,
          8
        ],
        [
          0,
          4,
          9
        ],
        [
          0,
          3,
          9
        ],
        [
          1,
          3,
          7
        ],
        [
          2,
          4,
          5
        ],
        [
          3,
          6,
          9
        ],
        [
          0,
          3,
          7
        ]
      ],
      "notes": 10,
      "cost": 20,
      "hits": 0,
      "prize": 0,
      "daily_pnl": -20,
      "reason": "组六10注->0命中 开奖808组三"
    },
    {
      "date": "2026-07-07",
      "draw": "2026178",
      "draw_nums": [
        2,
        6,
        6
      ],
      "draw_type": "组三",
      "recommendations": [
        [
          3,
          5,
          7
        ],
        [
          1,
          2,
          4
        ],
        [
          2,
          3,
          8
        ],
        [
          5,
          6,
          7
        ],
        [
          1,
          3,
          9
        ],
        [
          0,
          5,
          7
        ],
        [
          2,
          3,
          5
        ],
        [
          2,
          4,
          5
        ],
        [
          3,
          6,
          9
        ],
        [
          1,
          3,
          8
        ]
      ],
      "notes": 10,
      "cost": 20,
      "hits": 0,
      "prize": 0,
      "daily_pnl": -20,
      "reason": "组六10注->0命中 开奖266组三"
    },
    {
      "date": "2026-07-08",
      "draw": "2026179",
      "draw_nums": [
        9,
        9,
        3
      ],
      "draw_type": "组三",
      "recommendations": [
        [
          3,
          5,
          7
        ],
        [
          1,
          4,
          9
        ],
        [
          2,
          3,
          6
        ],
        [
          5,
          7,
          8
        ],
        [
          1,
          3,
          9
        ],
        [
          0,
          5,
          7
        ],
        [
          2,
          3,
          9
        ],
        [
          0,
          5,
          6
        ],
        [
          2,
          4,
          5
        ],
        [
          2,
          3,
          5
        ]
      ],
      "notes": 10,
      "cost": 20,
      "hits": 0,
      "prize": 0,
      "daily_pnl": -20,
      "reason": "组六10注->0命中 开奖993组三"
    },
    {
      "date": "2026-07-09",
      "draw": "2026180",
      "draw_nums": [
        5,
        2,
        0
      ],
      "draw_type": "组六",
      "recommendations": [
        [
          4,
          5,
          7
        ],
        [
          0,
          1,
          8
        ],
        [
          2,
          5,
          6
        ],
        [
          0,
          5,
          8
        ],
        [
          0,
          5,
          7
        ],
        [
          2,
          5,
          9
        ],
        [
          1,
          6,
          7
        ],
        [
          4,
          5,
          9
        ],
        [
          2,
          3,
          5
        ],
        [
          2,
          4,
          5
        ]
      ],
      "notes": 10,
      "cost": 20,
      "hits": 0,
      "prize": 0,
      "daily_pnl": -20,
      "reason": "组六10注->0命中 开奖520组六"
    },
    {
      "date": "2026-07-10",
      "draw": "2026181",
      "draw_nums": [
        8,
        1,
        8
      ],
      "draw_type": "组三",
      "recommendations": [
        [
          1,
          4,
          7
        ],
        [
          6,
          8,
          9
        ],
        [
          2,
          6,
          7
        ],
        [
          4,
          7,
          8
        ],
        [
          0,
          6,
          7
        ],
        [
          0,
          4,
          8
        ],
        [
          0,
          2,
          7
        ],
        [
          0,
          4,
          6
        ],
        [
          2,
          4,
          5
        ],
        [
          1,
          2,
          7
        ]
      ],
      "notes": 10,
      "cost": 20,
      "hits": 0,
      "prize": 0,
      "daily_pnl": -20,
      "reason": "组六10注->0命中 开奖818组三"
    },
    {
      "date": "2026-07-11",
      "draw": "2026182",
      "draw_nums": [
        6,
        6,
        2
      ],
      "draw_type": "组三",
      "recommendations": [
        [
          4,
          6,
          7
        ],
        [
          2,
          3,
          9
        ],
        [
          2,
          7,
          8
        ],
        [
          0,
          6,
          7
        ],
        [
          0,
          4,
          8
        ],
        [
          1,
          7,
          8
        ],
        [
          2,
          4,
          8
        ],
        [
          2,
          5,
          8
        ],
        [
          4,
          8,
          9
        ],
        [
          1,
          2,
          7
        ]
      ],
      "notes": 10,
      "cost": 20,
      "hits": 0,
      "prize": 0,
      "daily_pnl": -20,
      "reason": "组六10注->0命中 开奖662组三"
    },
    {
      "date": "2026-07-12",
      "draw": "2026183",
      "draw_nums": [
        9,
        2,
        3
      ],
      "draw_type": "组六",
      "recommendations": [
        [
          4,
          7,
          9
        ],
        [
          0,
          3,
          5
        ],
        [
          2,
          6,
          7
        ],
        [
          4,
          7,
          8
        ],
        [
          0,
          6,
          7
        ],
        [
          0,
          4,
          8
        ],
        [
          2,
          5,
          6
        ],
        [
          2,
          8,
          9
        ],
        [
          1,
          2,
          7
        ],
        [
          2,
          3,
          7
        ]
      ],
      "notes": 10,
      "cost": 20,
      "hits": 0,
      "prize": 0,
      "daily_pnl": -20,
      "reason": "组六10注->0命中 开奖923组六"
    },
    {
      "date": "2026-07-13",
      "draw": "2026184",
      "draw_nums": [
        9,
        0,
        2
      ],
      "draw_type": "组六",
      "recommendations": [
        [
          0,
          4,
          7
        ],
        [
          1,
          5,
          8
        ],
        [
          2,
          6,
          7
        ],
        [
          4,
          8,
          9
        ],
        [
          0,
          6,
          7
        ],
        [
          0,
          4,
          8
        ],
        [
          2,
          5,
          6
        ],
        [
          2,
          8,
          9
        ],
        [
          1,
          2,
          7
        ],
        [
          2,
          3,
          7
        ]
      ],
      "notes": 10,
      "cost": 20,
      "hits": 0,
      "prize": 0,
      "daily_pnl": -20,
      "reason": "组六10注->0命中 开奖902组六"
    },
    {
      "date": "2026-07-14",
      "draw": "2026185",
      "draw_nums": [
        3,
        9,
        7
      ],
      "draw_type": "组六",
      "recommendations": [
        [
          4,
          5,
          7
        ],
        [
          1,
          6,
          8
        ],
        [
          2,
          6,
          7
        ],
        [
          4,
          8,
          9
        ],
        [
          0,
          6,
          7
        ],
        [
          0,
          4,
          8
        ],
        [
          1,
          2,
          7
        ],
        [
          1,
          4,
          6
        ],
        [
          5,
          8,
          9
        ],
        [
          2,
          3,
          7
        ]
      ],
      "notes": 10,
      "cost": 20,
      "hits": 0,
      "prize": 0,
      "daily_pnl": -20,
      "reason": "组六10注->0命中 开奖397组六"
    },
    {
      "date": "2026-07-15",
      "draw": "待开奖",
      "draw_nums": [],
      "draw_type": "",
      "recommendations": [
        [
          1,
          4,
          5
        ],
        [
          0,
          4,
          5
        ],
        [
          2,
          4,
          5
        ],
        [
          1,
          4,
          8
        ],
        [
          0,
          1,
          4
        ],
        [
          4,
          5,
          8
        ],
        [
          2,
          4,
          6
        ],
        [
          4,
          6,
          9
        ],
        [
          0,
          2,
          8
        ],
        [
          2,
          5,
          8
        ]
      ],
      "notes": 10,
      "cost": 20,
      "hits": null,
      "prize": null,
      "daily_pnl": null,
      "reason": "Rule4优先(组六3连=强推), 10注组六, 锚点4(缺10期)"
    }
  ],
  "summary": {
    "total_days": 34,
    "settled_days": 33,
    "active_days": 24,
    "total_bets": 227,
    "total_cost": 454,
    "total_hits": 2,
    "total_prize": 320,
    "net_pnl": -134,
    "pending_bets": 10,
    "pending_cost": 20,
    "last_settled": "2026-07-14",
    "last_hit": "6/26 [1,3,6]→631 | 6/29 [0,5,8]→805"
  }
}